jansbckernel/__init__.py
jansbckernel/__main__.py
jansbckernel/install_kernelspec.py
jansbckernel/kernel.py
jansbckernel-0.2.0.dist-info/LICENSE
jansbckernel-0.2.0.dist-info/METADATA
jansbckernel-0.2.0.dist-info/WHEEL
jansbckernel-0.2.0.dist-info/entry_points.txt
jansbckernel-0.2.0.dist-info/top_level.txt
jansbckernel-0.2.0.dist-info/RECORD
