Metadata-Version: 2.1
Name: jansbckernel
Version: 0.2.0
Summary: A rough bc kernel.
Author-email: Jan Arman Parpin <is@hidden.com>
Project-URL: Homepage, https://github.com/jans-code/jansbckernel
Project-URL: Bug Tracker, https://github.com/jans-code/jansbckernel/issues
Classifier: Programming Language :: Python :: 3
Classifier: License :: OSI Approved :: MIT License
Classifier: Operating System :: POSIX :: Linux
Classifier: Framework :: Jupyter :: JupyterLab :: 3
Classifier: Framework :: Jupyter :: JupyterLab :: 4
Requires-Python: >=3.7
License-File: LICENSE
Requires-Dist: ipykernel
